[
  {
    "py/object": "model.group.Group",
    "header": "",
    "id": null,
    "name": ""
  },
  {
    "py/object": "model.group.Group",
    "header": "header9Ll2ekQC1Q41MtXB",
    "id": null,
    "name": "namexZEkum"
  },
  {
    "py/object": "model.group.Group",
    "header": "headerHsuiwzBZwdNs3nLERD",
    "id": null,
    "name": "nameHR6TT5v"
  },
  {
    "py/object": "model.group.Group",
    "header": "headerZnjbvIST7sz",
    "id": null,
    "name": "nameIt12t"
  },
  {
    "py/object": "model.group.Group",
    "header": "headerDiz6ftEoqLduu0V",
    "id": null,
    "name": "namevR40lkp"
  },
  {
    "py/object": "model.group.Group",
    "header": "headeromgKbbRbr0XiGo60",
    "id": null,
    "name": "name2FbcmS"
  }
]